sim/verilator/build/results/coverage/block_ram_model.v
//      // verilator_coverage annotation
        // =======================================================================
        // Module:      Block RAM (model)
        // Project:     Ripple-32
        // Description: This block RAM can be preloaded with the readmemh function. 
        // =======================================================================
        
        module block_ram_model #(
          parameter  ADDR_WIDTH   = 12,
          parameter  DATA_WIDTH   = 32,
          parameter  INIT_VALUE   = 0,
          parameter  MEM_FILE     = "",
          parameter  RAM_WORDS    = 1 << ADDR_WIDTH // Use full address space 
        )(
 002629   input  wire                     clk,
~000051   input  wire  [ADDR_WIDTH-1:0]   addr,
~000054   input  wire  [DATA_WIDTH-1:0]   wdata,
%000000   input  wire  [(DATA_WIDTH-1):0] wstrb, // TODO - enforce byte strobe
 000400   input  wire                     en,
 000200   input  wire                     wr_en,
~000054   output reg   [DATA_WIDTH-1:0]   rdata
        );
        
          integer i;
          localparam BSTRB_WIDTH = (DATA_WIDTH+7)/8;
          localparam MAX_RAM_SIZE   = 1 << ADDR_WIDTH;
        
          reg [DATA_WIDTH-1:0] mem [MAX_RAM_SIZE-1:0];
        
          // Initial value assignment
%000001   initial begin  
%000001     if (MEM_FILE != "") begin
%000000         $readmemh(MEM_FILE, mem);
%000001     end else begin
~000010       for (i = 0; i < RAM_WORDS; i=i+1) begin
 000010         mem[i] = INIT_VALUE;
              end
            end
          end
        
          // TODO - Warn/error if you a read is attempted from outside of the valid index
        
          // TODO add byte strobe to the RAM write acess
        
          // RAM write
 001315   always @(posedge clk ) begin
 001215     if (en && wr_en) begin
 000100       mem[addr] <= wdata;
            end
          end
        
          // RAM read
 001315   always @(posedge clk ) begin
 001215     if (en && ~wr_en) begin
 000100       rdata <= mem[addr];
            end
          end
        
        endmodule

sim/verilator/build/results/coverage/block_ram_model_wtb.v
//      // verilator_coverage annotation
        // Auto-generated Verilog Testbench Wrapper - Coraltb 
         
        `timescale 1ns/1ns 
        
        module block_ram_model_wtb;
        
          // block_ram_model instantation signals
 002629   reg         clk;
~000051   reg  [7:0]  addr;
~000054   reg  [31:0] wdata;
%000000   reg  [31:0]  wstrb;
 000400   reg         en;
 000200   reg         wr_en;
~000054   wire [31:0] rdata;
        
          block_ram_model #(
            .ADDR_WIDTH(8),
            .DATA_WIDTH(32),
            .INIT_VALUE(0),
            .RAM_WORDS(10)
          ) dut (
            .clk(clk),
            .addr(addr),
            .wdata(wdata),
            .wstrb(wstrb),
            .en(en),
            .wr_en(wr_en),
            .rdata(rdata)
          );
        
%000001   initial begin
%000001     $dumpvars(0, block_ram_model_wtb);
          end
        
        endmodule

sim/verilator/build/results/dump.vcd
$version Generated by VerilatedVcd $end
$timescale 1ns $end
 $scope module block_ram_model_wtb $end
  $var wire 1 # clk $end
  $var wire 8 $ addr [7:0] $end
  $var wire 32 % wdata [31:0] $end
  $var wire 32 & wstrb [31:0] $end
  $var wire 1 ' en $end
  $var wire 1 ( wr_en $end
  $var wire 32 ) rdata [31:0] $end
  $scope module dut $end
   $var wire 32 2 ADDR_WIDTH [31:0] $end
   $var wire 32 3 DATA_WIDTH [31:0] $end
   $var wire 32 4 INIT_VALUE [31:0] $end
   $var wire 8 5 MEM_FILE [7:0] $end
   $var wire 32 6 RAM_WORDS [31:0] $end
   $var wire 1 * clk $end
   $var wire 8 + addr [7:0] $end
   $var wire 32 , wdata [31:0] $end
   $var wire 32 - wstrb [31:0] $end
   $var wire 1 . en $end
   $var wire 1 / wr_en $end
   $var wire 32 0 rdata [31:0] $end
   $var wire 32 1 i [31:0] $end
   $var wire 32 7 BSTRB_WIDTH [31:0] $end
   $var wire 32 8 MAX_RAM_SIZE [31:0] $end
  $upscope $end
 $upscope $end
$enddefinitions $end


#0
1#
b00000101 $
b00000000000000000000000000001011 %
b00000000000000000000000000000000 &
0'
1(
b00000000000000000000000000000000 )
1*
b00000101 +
b00000000000000000000000000001011 ,
b00000000000000000000000000000000 -
0.
1/
b00000000000000000000000000000000 0
b00000000000000000000000000001010 1
b00000000000000000000000000001000 2
b00000000000000000000000000100000 3
b00000000000000000000000000000000 4
b00000000 5
b00000000000000000000000000001010 6
b00000000000000000000000000000100 7
b00000000000000000000000100000000 8
#25
0#
0*
#50
1#
1*
#75
0#
0*
#100
1#
1*
#125
0#
0*
#150
1#
1*
#175
0#
0*
#200
1#
1*
#225
0#
0*
#250
1#
1*
#275
0#
0*
#300
1#
1*
#325
0#
0*
#350
1#
1*
#375
0#
0*
#400
1#
1'
0(
1*
1.
0/
#425
0#
0*
#450
1#
0'
b00000000000000000000000000001011 )
1*
0.
b00000000000000000000000000001011 0
#475
0#
0*
#500
1#
1*
#525
0#
0*
#550
1#
1*
#575
0#
0*
#600
1#
1*
#625
0#
0*
#650
1#
1*
#675
0#
0*
#700
1#
1*
#725
0#
0*
#750
1#
1*
#775
0#
0*
#800
1#
1*
#825
0#
0*
#850
1#
1*
#875
0#
0*
#900
1#
b00000000000000000000000000010101 %
1'
1(
1*
b00000000000000000000000000010101 ,
1.
1/
#925
0#
0*
#950
1#
0'
1*
0.
#975
0#
0*
#1000
1#
1*
#1025
0#
0*
#1050
1#
1*
#1075
0#
0*
#1100
1#
1*
#1125
0#
0*
#1150
1#
1*
#1175
0#
0*
#1200
1#
1*
#1225
0#
0*
#1250
1#
1*
#1275
0#
0*
#1300
1#
1*
#1325
0#
0*
#1350
1#
1'
0(
1*
1.
0/
#1375
0#
0*
#1400
1#
0'
b00000000000000000000000000010101 )
1*
0.
b00000000000000000000000000010101 0
#1425
0#
0*
#1450
1#
1*
#1475
0#
0*
#1500
1#
1*
#1525
0#
0*
#1550
1#
1*
#1575
0#
0*
#1600
1#
1*
#1625
0#
0*
#1650
1#
1*
#1675
0#
0*
#1700
1#
1*
#1725
0#
0*
#1750
1#
1*
#1775
0#
0*
#1800
1#
b00000100 $
b00000000000000000000000000011100 %
1'
1(
1*
b00000100 +
b00000000000000000000000000011100 ,
1.
1/
#1825
0#
0*
#1850
1#
0'
1*
0.
#1875
0#
0*
#1900
1#
1*
#1925
0#
0*
#1950
1#
1'
0(
1*
1.
0/
#1975
0#
0*
#2000
1#
0'
b00000000000000000000000000011100 )
1*
0.
b00000000000000000000000000011100 0
#2025
0#
0*
#2050
1#
1*
#2075
0#
0*
#2100
1#
1*
#2125
0#
0*
#2150
1#
1*
#2175
0#
0*
#2200
1#
1*
#2225
0#
0*
#2250
1#
1*
#2275
0#
0*
#2300
1#
b00000011 $
b00000000000000000000000000000110 %
1'
1(
1*
b00000011 +
b00000000000000000000000000000110 ,
1.
1/
#2325
0#
0*
#2350
1#
0'
1*
0.
#2375
0#
0*
#2400
1#
1*
#2425
0#
0*
#2450
1#
1*
#2475
0#
0*
#2500
1#
1*
#2525
0#
0*
#2550
1#
1*
#2575
0#
0*
#2600
1#
1*
#2625
0#
0*
#2650
1#
1*
#2675
0#
0*
#2700
1#
1*
#2725
0#
0*
#2750
1#
1*
#2775
0#
0*
#2800
1#
1'
0(
1*
1.
0/
#2825
0#
0*
#2850
1#
0'
b00000000000000000000000000000110 )
1*
0.
b00000000000000000000000000000110 0
#2875
0#
0*
#2900
1#
1*
#2925
0#
0*
#2950
1#
1*
#2975
0#
0*
#3000
1#
1*
#3025
0#
0*
#3050
1#
1*
#3075
0#
0*
#3100
1#
1*
#3125
0#
0*
#3150
1#
1*
#3175
0#
0*
#3200
1#
b00001001 $
b00000000000000000000000000000000 %
1'
1(
1*
b00001001 +
b00000000000000000000000000000000 ,
1.
1/
#3225
0#
0*
#3250
1#
0'
1*
0.
#3275
0#
0*
#3300
1#
1*
#3325
0#
0*
#3350
1#
1*
#3375
0#
0*
#3400
1#
1*
#3425
0#
0*
#3450
1#
1*
#3475
0#
0*
#3500
1#
1*
#3525
0#
0*
#3550
1#
1*
#3575
0#
0*
#3600
1#
1*
#3625
0#
0*
#3650
1#
1*
#3675
0#
0*
#3700
1#
1'
0(
1*
1.
0/
#3725
0#
0*
#3750
1#
0'
b00000000000000000000000000000000 )
1*
0.
b00000000000000000000000000000000 0
#3775
0#
0*
#3800
1#
1*
#3825
0#
0*
#3850
1#
1*
#3875
0#
0*
#3900
1#
1*
#3925
0#
0*
#3950
1#
1*
#3975
0#
0*
#4000
1#
1*
#4025
0#
0*
#4050
1#
1*
#4075
0#
0*
#4100
1#
1*
#4125
0#
0*
#4150
1#
1*
#4175
0#
0*
#4200
1#
1*
#4225
0#
0*
#4250
1#
1'
1(
1*
1.
1/
#4275
0#
0*
#4300
1#
0'
1*
0.
#4325
0#
0*
#4350
1#
1*
#4375
0#
0*
#4400
1#
1*
#4425
0#
0*
#4450
1#
1*
#4475
0#
0*
#4500
1#
1*
#4525
0#
0*
#4550
1#
1'
0(
1*
1.
0/
#4575
0#
0*
#4600
1#
0'
1*
0.
#4625
0#
0*
#4650
1#
b00000000 $
b00000000000000000000000000010100 %
1'
1(
1*
b00000000 +
b00000000000000000000000000010100 ,
1.
1/
#4675
0#
0*
#4700
1#
0'
1*
0.
#4725
0#
0*
#4750
1#
1*
#4775
0#
0*
#4800
1#
1*
#4825
0#
0*
#4850
1#
1*
#4875
0#
0*
#4900
1#
1*
#4925
0#
0*
#4950
1#
1*
#4975
0#
0*
#5000
1#
1*
#5025
0#
0*
#5050
1#
1'
0(
1*
1.
0/
#5075
0#
0*
#5100
1#
0'
b00000000000000000000000000010100 )
1*
0.
b00000000000000000000000000010100 0
#5125
0#
0*
#5150
1#
1*
#5175
0#
0*
#5200
1#
1*
#5225
0#
0*
#5250
1#
1*
#5275
0#
0*
#5300
1#
1*
#5325
0#
0*
#5350
1#
1*
#5375
0#
0*
#5400
1#
1*
#5425
0#
0*
#5450
1#
1*
#5475
0#
0*
#5500
1#
1*
#5525
0#
0*
#5550
1#
1*
#5575
0#
0*
#5600
1#
b00000101 $
b00000000000000000000000000011011 %
1'
1(
1*
b00000101 +
b00000000000000000000000000011011 ,
1.
1/
#5625
0#
0*
#5650
1#
0'
1*
0.
#5675
0#
0*
#5700
1#
1*
#5725
0#
0*
#5750
1#
1*
#5775
0#
0*
#5800
1#
1*
#5825
0#
0*
#5850
1#
1*
#5875
0#
0*
#5900
1#
1*
#5925
0#
0*
#5950
1#
1*
#5975
0#
0*
#6000
1#
1*
#6025
0#
0*
#6050
1#
1*
#6075
0#
0*
#6100
1#
1'
0(
1*
1.
0/
#6125
0#
0*
#6150
1#
0'
b00000000000000000000000000011011 )
1*
0.
b00000000000000000000000000011011 0
#6175
0#
0*
#6200
1#
1*
#6225
0#
0*
#6250
1#
b00000011 $
b00000000000000000000000000010111 %
1'
1(
1*
b00000011 +
b00000000000000000000000000010111 ,
1.
1/
#6275
0#
0*
#6300
1#
0'
1*
0.
#6325
0#
0*
#6350
1#
1*
#6375
0#
0*
#6400
1#
1*
#6425
0#
0*
#6450
1#
1*
#6475
0#
0*
#6500
1#
1*
#6525
0#
0*
#6550
1#
1*
#6575
0#
0*
#6600
1#
1*
#6625
0#
0*
#6650
1#
1*
#6675
0#
0*
#6700
1#
1*
#6725
0#
0*
#6750
1#
1'
0(
1*
1.
0/
#6775
0#
0*
#6800
1#
0'
b00000000000000000000000000010111 )
1*
0.
b00000000000000000000000000010111 0
#6825
0#
0*
#6850
1#
1*
#6875
0#
0*
#6900
1#
1*
#6925
0#
0*
#6950
1#
1*
#6975
0#
0*
#7000
1#
1*
#7025
0#
0*
#7050
1#
1*
#7075
0#
0*
#7100
1#
1*
#7125
0#
0*
#7150
1#
b00001001 $
b00000000000000000000000000000111 %
1'
1(
1*
b00001001 +
b00000000000000000000000000000111 ,
1.
1/
#7175
0#
0*
#7200
1#
0'
1*
0.
#7225
0#
0*
#7250
1#
1*
#7275
0#
0*
#7300
1#
1*
#7325
0#
0*
#7350
1#
1*
#7375
0#
0*
#7400
1#
1'
0(
1*
1.
0/
#7425
0#
0*
#7450
1#
0'
b00000000000000000000000000000111 )
1*
0.
b00000000000000000000000000000111 0
#7475
0#
0*
#7500
1#
1*
#7525
0#
0*
#7550
1#
1*
#7575
0#
0*
#7600
1#
1*
#7625
0#
0*
#7650
1#
1*
#7675
0#
0*
#7700
1#
1*
#7725
0#
0*
#7750
1#
b00000011 $
b00000000000000000000000000100001 %
1'
1(
1*
b00000011 +
b00000000000000000000000000100001 ,
1.
1/
#7775
0#
0*
#7800
1#
0'
1*
0.
#7825
0#
0*
#7850
1#
1*
#7875
0#
0*
#7900
1#
1*
#7925
0#
0*
#7950
1#
1*
#7975
0#
0*
#8000
1#
1'
0(
1*
1.
0/
#8025
0#
0*
#8050
1#
0'
b00000000000000000000000000100001 )
1*
0.
b00000000000000000000000000100001 0
#8075
0#
0*
#8100
1#
1*
#8125
0#
0*
#8150
1#
1*
#8175
0#
0*
#8200
1#
1*
#8225
0#
0*
#8250
1#
b00000001 $
b00000000000000000000000000011110 %
1'
1(
1*
b00000001 +
b00000000000000000000000000011110 ,
1.
1/
#8275
0#
0*
#8300
1#
0'
1*
0.
#8325
0#
0*
#8350
1#
1*
#8375
0#
0*
#8400
1#
1*
#8425
0#
0*
#8450
1#
1*
#8475
0#
0*
#8500
1#
1*
#8525
0#
0*
#8550
1#
1*
#8575
0#
0*
#8600
1#
1*
#8625
0#
0*
#8650
1#
1'
0(
1*
1.
0/
#8675
0#
0*
#8700
1#
0'
b00000000000000000000000000011110 )
1*
0.
b00000000000000000000000000011110 0
#8725
0#
0*
#8750
1#
b00000110 $
b00000000000000000000000000001001 %
1'
1(
1*
b00000110 +
b00000000000000000000000000001001 ,
1.
1/
#8775
0#
0*
#8800
1#
0'
1*
0.
#8825
0#
0*
#8850
1#
1*
#8875
0#
0*
#8900
1#
1*
#8925
0#
0*
#8950
1#
1*
#8975
0#
0*
#9000
1#
1*
#9025
0#
0*
#9050
1#
1*
#9075
0#
0*
#9100
1#
1*
#9125
0#
0*
#9150
1#
1*
#9175
0#
0*
#9200
1#
1'
0(
1*
1.
0/
#9225
0#
0*
#9250
1#
0'
b00000000000000000000000000001001 )
1*
0.
b00000000000000000000000000001001 0
#9275
0#
0*
#9300
1#
1*
#9325
0#
0*
#9350
1#
1*
#9375
0#
0*
#9400
1#
1*
#9425
0#
0*
#9450
1#
1*
#9475
0#
0*
#9500
1#
1*
#9525
0#
0*
#9550
1#
1*
#9575
0#
0*
#9600
1#
1*
#9625
0#
0*
#9650
1#
1*
#9675
0#
0*
#9700
1#
b00000101 $
b00000000000000000000000000001011 %
1'
1(
1*
b00000101 +
b00000000000000000000000000001011 ,
1.
1/
#9725
0#
0*
#9750
1#
0'
1*
0.
#9775
0#
0*
#9800
1#
1*
#9825
0#
0*
#9850
1#
1*
#9875
0#
0*
#9900
1#
1*
#9925
0#
0*
#9950
1#
1*
#9975
0#
0*
#10000
1#
1*
#10025
0#
0*
#10050
1#
1*
#10075
0#
0*
#10100
1#
1*
#10125
0#
0*
#10150
1#
1*
#10175
0#
0*
#10200
1#
1'
0(
1*
1.
0/
#10225
0#
0*
#10250
1#
0'
b00000000000000000000000000001011 )
1*
0.
b00000000000000000000000000001011 0
#10275
0#
0*
#10300
1#
b00000000000000000000000000010000 %
1'
1(
1*
b00000000000000000000000000010000 ,
1.
1/
#10325
0#
0*
#10350
1#
0'
1*
0.
#10375
0#
0*
#10400
1#
1*
#10425
0#
0*
#10450
1#
1*
#10475
0#
0*
#10500
1#
1*
#10525
0#
0*
#10550
1#
1*
#10575
0#
0*
#10600
1#
1*
#10625
0#
0*
#10650
1#
1*
#10675
0#
0*
#10700
1#
1*
#10725
0#
0*
#10750
1#
1*
#10775
0#
0*
#10800
1#
1'
0(
1*
1.
0/
#10825
0#
0*
#10850
1#
0'
b00000000000000000000000000010000 )
1*
0.
b00000000000000000000000000010000 0
#10875
0#
0*
#10900
1#
1*
#10925
0#
0*
#10950
1#
1*
#10975
0#
0*
#11000
1#
1*
#11025
0#
0*
#11050
1#
1*
#11075
0#
0*
#11100
1#
1*
#11125
0#
0*
#11150
1#
1*
#11175
0#
0*
#11200
1#
1*
#11225
0#
0*
#11250
1#
1*
#11275
0#
0*
#11300
1#
b00000010 $
b00000000000000000000000000011100 %
1'
1(
1*
b00000010 +
b00000000000000000000000000011100 ,
1.
1/
#11325
0#
0*
#11350
1#
0'
1*
0.
#11375
0#
0*
#11400
1#
1*
#11425
0#
0*
#11450
1#
1'
0(
1*
1.
0/
#11475
0#
0*
#11500
1#
0'
b00000000000000000000000000011100 )
1*
0.
b00000000000000000000000000011100 0
#11525
0#
0*
#11550
1#
1*
#11575
0#
0*
#11600
1#
1*
#11625
0#
0*
#11650
1#
b00000111 $
b00000000000000000000000000100001 %
1'
1(
1*
b00000111 +
b00000000000000000000000000100001 ,
1.
1/
#11675
0#
0*
#11700
1#
0'
1*
0.
#11725
0#
0*
#11750
1#
1*
#11775
0#
0*
#11800
1#
1*
#11825
0#
0*
#11850
1#
1*
#11875
0#
0*
#11900
1#
1'
0(
1*
1.
0/
#11925
0#
0*
#11950
1#
0'
b00000000000000000000000000100001 )
1*
0.
b00000000000000000000000000100001 0
#11975
0#
0*
#12000
1#
1*
#12025
0#
0*
#12050
1#
1*
#12075
0#
0*
#12100
1#
1*
#12125
0#
0*
#12150
1#
1*
#12175
0#
0*
#12200
1#
1*
#12225
0#
0*
#12250
1#
1*
#12275
0#
0*
#12300
1#
b00000001 $
b00000000000000000000000000000111 %
1'
1(
1*
b00000001 +
b00000000000000000000000000000111 ,
1.
1/
#12325
0#
0*
#12350
1#
0'
1*
0.
#12375
0#
0*
#12400
1#
1*
#12425
0#
0*
#12450
1#
1'
0(
1*
1.
0/
#12475
0#
0*
#12500
1#
0'
b00000000000000000000000000000111 )
1*
0.
b00000000000000000000000000000111 0
#12525
0#
0*
#12550
1#
1*
#12575
0#
0*
#12600
1#
1*
#12625
0#
0*
#12650
1#
1*
#12675
0#
0*
#12700
1#
b00000011 $
b00000000000000000000000000000101 %
1'
1(
1*
b00000011 +
b00000000000000000000000000000101 ,
1.
1/
#12725
0#
0*
#12750
1#
0'
1*
0.
#12775
0#
0*
#12800
1#
1*
#12825
0#
0*
#12850
1#
1*
#12875
0#
0*
#12900
1#
1*
#12925
0#
0*
#12950
1#
1*
#12975
0#
0*
#13000
1#
1*
#13025
0#
0*
#13050
1#
1*
#13075
0#
0*
#13100
1#
1*
#13125
0#
0*
#13150
1#
1*
#13175
0#
0*
#13200
1#
1'
0(
1*
1.
0/
#13225
0#
0*
#13250
1#
0'
b00000000000000000000000000000101 )
1*
0.
b00000000000000000000000000000101 0
#13275
0#
0*
#13300
1#
1*
#13325
0#
0*
#13350
1#
1*
#13375
0#
0*
#13400
1#
1*
#13425
0#
0*
#13450
1#
1*
#13475
0#
0*
#13500
1#
1*
#13525
0#
0*
#13550
1#
b00001000 $
b00000000000000000000000000011110 %
1'
1(
1*
b00001000 +
b00000000000000000000000000011110 ,
1.
1/
#13575
0#
0*
#13600
1#
0'
1*
0.
#13625
0#
0*
#13650
1#
1*
#13675
0#
0*
#13700
1#
1*
#13725
0#
0*
#13750
1#
1*
#13775
0#
0*
#13800
1#
1*
#13825
0#
0*
#13850
1#
1*
#13875
0#
0*
#13900
1#
1*
#13925
0#
0*
#13950
1#
1*
#13975
0#
0*
#14000
1#
1*
#14025
0#
0*
#14050
1#
1*
#14075
0#
0*
#14100
1#
1'
0(
1*
1.
0/
#14125
0#
0*
#14150
1#
0'
b00000000000000000000000000011110 )
1*
0.
b00000000000000000000000000011110 0
#14175
0#
0*
#14200
1#
1*
#14225
0#
0*
#14250
1#
1*
#14275
0#
0*
#14300
1#
1*
#14325
0#
0*
#14350
1#
b00000010 $
b00000000000000000000000000010001 %
1'
1(
1*
b00000010 +
b00000000000000000000000000010001 ,
1.
1/
#14375
0#
0*
#14400
1#
0'
1*
0.
#14425
0#
0*
#14450
1#
1*
#14475
0#
0*
#14500
1#
1*
#14525
0#
0*
#14550
1#
1*
#14575
0#
0*
#14600
1#
1*
#14625
0#
0*
#14650
1#
1*
#14675
0#
0*
#14700
1#
1'
0(
1*
1.
0/
#14725
0#
0*
#14750
1#
0'
b00000000000000000000000000010001 )
1*
0.
b00000000000000000000000000010001 0
#14775
0#
0*
#14800
1#
1*
#14825
0#
0*
#14850
1#
1*
#14875
0#
0*
#14900
1#
1*
#14925
0#
0*
#14950
1#
1*
#14975
0#
0*
#15000
1#
1*
#15025
0#
0*
#15050
1#
1*
#15075
0#
0*
#15100
1#
1*
#15125
0#
0*
#15150
1#
1*
#15175
0#
0*
#15200
1#
1*
#15225
0#
0*
#15250
1#
b00000000 $
b00000000000000000000000000000000 %
1'
1(
1*
b00000000 +
b00000000000000000000000000000000 ,
1.
1/
#15275
0#
0*
#15300
1#
0'
1*
0.
#15325
0#
0*
#15350
1#
1*
#15375
0#
0*
#15400
1#
1*
#15425
0#
0*
#15450
1#
1*
#15475
0#
0*
#15500
1#
1*
#15525
0#
0*
#15550
1#
1*
#15575
0#
0*
#15600
1#
1*
#15625
0#
0*
#15650
1#
1*
#15675
0#
0*
#15700
1#
1'
0(
1*
1.
0/
#15725
0#
0*
#15750
1#
0'
b00000000000000000000000000000000 )
1*
0.
b00000000000000000000000000000000 0
#15775
0#
0*
#15800
1#
1*
#15825
0#
0*
#15850
1#
1*
#15875
0#
0*
#15900
1#
1*
#15925
0#
0*
#15950
1#
1*
#15975
0#
0*
#16000
1#
b00001000 $
b00000000000000000000000000011000 %
1'
1(
1*
b00001000 +
b00000000000000000000000000011000 ,
1.
1/
#16025
0#
0*
#16050
1#
0'
1*
0.
#16075
0#
0*
#16100
1#
1*
#16125
0#
0*
#16150
1#
1*
#16175
0#
0*
#16200
1#
1*
#16225
0#
0*
#16250
1#
1'
0(
1*
1.
0/
#16275
0#
0*
#16300
1#
0'
b00000000000000000000000000011000 )
1*
0.
b00000000000000000000000000011000 0
#16325
0#
0*
#16350
1#
1*
#16375
0#
0*
#16400
1#
1*
#16425
0#
0*
#16450
1#
1*
#16475
0#
0*
#16500
1#
1*
#16525
0#
0*
#16550
1#
b00000100 $
b00000000000000000000000000000110 %
1'
1(
1*
b00000100 +
b00000000000000000000000000000110 ,
1.
1/
#16575
0#
0*
#16600
1#
0'
1*
0.
#16625
0#
0*
#16650
1#
1*
#16675
0#
0*
#16700
1#
1*
#16725
0#
0*
#16750
1#
1*
#16775
0#
0*
#16800
1#
1'
0(
1*
1.
0/
#16825
0#
0*
#16850
1#
0'
b00000000000000000000000000000110 )
1*
0.
b00000000000000000000000000000110 0
#16875
0#
0*
#16900
1#
1*
#16925
0#
0*
#16950
1#
1*
#16975
0#
0*
#17000
1#
b00000111 $
b00000000000000000000000000000011 %
1'
1(
1*
b00000111 +
b00000000000000000000000000000011 ,
1.
1/
#17025
0#
0*
#17050
1#
0'
1*
0.
#17075
0#
0*
#17100
1#
1*
#17125
0#
0*
#17150
1#
1*
#17175
0#
0*
#17200
1#
1'
0(
1*
1.
0/
#17225
0#
0*
#17250
1#
0'
b00000000000000000000000000000011 )
1*
0.
b00000000000000000000000000000011 0
#17275
0#
0*
#17300
1#
1*
#17325
0#
0*
#17350
1#
1*
#17375
0#
0*
#17400
1#
b00000001 $
b00000000000000000000000000001101 %
1'
1(
1*
b00000001 +
b00000000000000000000000000001101 ,
1.
1/
#17425
0#
0*
#17450
1#
0'
1*
0.
#17475
0#
0*
#17500
1#
1*
#17525
0#
0*
#17550
1#
1*
#17575
0#
0*
#17600
1#
1*
#17625
0#
0*
#17650
1#
1'
0(
1*
1.
0/
#17675
0#
0*
#17700
1#
0'
b00000000000000000000000000001101 )
1*
0.
b00000000000000000000000000001101 0
#17725
0#
0*
#17750
1#
1*
#17775
0#
0*
#17800
1#
1*
#17825
0#
0*
#17850
1#
1*
#17875
0#
0*
#17900
1#
1*
#17925
0#
0*
#17950
1#
1*
#17975
0#
0*
#18000
1#
1*
#18025
0#
0*
#18050
1#
1*
#18075
0#
0*
#18100
1#
1*
#18125
0#
0*
#18150
1#
1*
#18175
0#
0*
#18200
1#
b00000000 $
b00000000000000000000000000000111 %
1'
1(
1*
b00000000 +
b00000000000000000000000000000111 ,
1.
1/
#18225
0#
0*
#18250
1#
0'
1*
0.
#18275
0#
0*
#18300
1#
1*
#18325
0#
0*
#18350
1#
1'
0(
1*
1.
0/
#18375
0#
0*
#18400
1#
0'
b00000000000000000000000000000111 )
1*
0.
b00000000000000000000000000000111 0
#18425
0#
0*
#18450
1#
b00000111 $
b00000000000000000000000000100000 %
1'
1(
1*
b00000111 +
b00000000000000000000000000100000 ,
1.
1/
#18475
0#
0*
#18500
1#
0'
1*
0.
#18525
0#
0*
#18550
1#
1*
#18575
0#
0*
#18600
1#
1*
#18625
0#
0*
#18650
1#
1*
#18675
0#
0*
#18700
1#
1*
#18725
0#
0*
#18750
1#
1*
#18775
0#
0*
#18800
1#
1*
#18825
0#
0*
#18850
1#
1*
#18875
0#
0*
#18900
1#
1*
#18925
0#
0*
#18950
1#
1*
#18975
0#
0*
#19000
1#
1'
0(
1*
1.
0/
#19025
0#
0*
#19050
1#
0'
b00000000000000000000000000100000 )
1*
0.
b00000000000000000000000000100000 0
#19075
0#
0*
#19100
1#
b00000100 $
b00000000000000000000000000001110 %
1'
1(
1*
b00000100 +
b00000000000000000000000000001110 ,
1.
1/
#19125
0#
0*
#19150
1#
0'
1*
0.
#19175
0#
0*
#19200
1#
1*
#19225
0#
0*
#19250
1#
1*
#19275
0#
0*
#19300
1#
1*
#19325
0#
0*
#19350
1#
1*
#19375
0#
0*
#19400
1#
1*
#19425
0#
0*
#19450
1#
1*
#19475
0#
0*
#19500
1#
1*
#19525
0#
0*
#19550
1#
1'
0(
1*
1.
0/
#19575
0#
0*
#19600
1#
0'
b00000000000000000000000000001110 )
1*
0.
b00000000000000000000000000001110 0
#19625
0#
0*
#19650
1#
1*
#19675
0#
0*
#19700
1#
1*
#19725
0#
0*
#19750
1#
1*
#19775
0#
0*
#19800
1#
1*
#19825
0#
0*
#19850
1#
1*
#19875
0#
0*
#19900
1#
1*
#19925
0#
0*
#19950
1#
1*
#19975
0#
0*
#20000
1#
1*
#20025
0#
0*
#20050
1#
b00000110 $
b00000000000000000000000000011000 %
1'
1(
1*
b00000110 +
b00000000000000000000000000011000 ,
1.
1/
#20075
0#
0*
#20100
1#
0'
1*
0.
#20125
0#
0*
#20150
1#
1*
#20175
0#
0*
#20200
1#
1*
#20225
0#
0*
#20250
1#
1*
#20275
0#
0*
#20300
1#
1*
#20325
0#
0*
#20350
1#
1*
#20375
0#
0*
#20400
1#
1*
#20425
0#
0*
#20450
1#
1*
#20475
0#
0*
#20500
1#
1*
#20525
0#
0*
#20550
1#
1*
#20575
0#
0*
#20600
1#
1'
0(
1*
1.
0/
#20625
0#
0*
#20650
1#
0'
b00000000000000000000000000011000 )
1*
0.
b00000000000000000000000000011000 0
#20675
0#
0*
#20700
1#
b00000101 $
b00000000000000000000000000010100 %
1'
1(
1*
b00000101 +
b00000000000000000000000000010100 ,
1.
1/
#20725
0#
0*
#20750
1#
0'
1*
0.
#20775
0#
0*
#20800
1#
1*
#20825
0#
0*
#20850
1#
1'
0(
1*
1.
0/
#20875
0#
0*
#20900
1#
0'
b00000000000000000000000000010100 )
1*
0.
b00000000000000000000000000010100 0
#20925
0#
0*
#20950
1#
1*
#20975
0#
0*
#21000
1#
1*
#21025
0#
0*
#21050
1#
1*
#21075
0#
0*
#21100
1#
1*
#21125
0#
0*
#21150
1#
1*
#21175
0#
0*
#21200
1#
1*
#21225
0#
0*
#21250
1#
1*
#21275
0#
0*
#21300
1#
b00000010 $
b00000000000000000000000000000011 %
1'
1(
1*
b00000010 +
b00000000000000000000000000000011 ,
1.
1/
#21325
0#
0*
#21350
1#
0'
1*
0.
#21375
0#
0*
#21400
1#
1*
#21425
0#
0*
#21450
1#
1*
#21475
0#
0*
#21500
1#
1'
0(
1*
1.
0/
#21525
0#
0*
#21550
1#
0'
b00000000000000000000000000000011 )
1*
0.
b00000000000000000000000000000011 0
#21575
0#
0*
#21600
1#
1*
#21625
0#
0*
#21650
1#
1*
#21675
0#
0*
#21700
1#
1*
#21725
0#
0*
#21750
1#
1*
#21775
0#
0*
#21800
1#
b00001000 $
1'
1(
1*
b00001000 +
1.
1/
#21825
0#
0*
#21850
1#
0'
1*
0.
#21875
0#
0*
#21900
1#
1*
#21925
0#
0*
#21950
1#
1*
#21975
0#
0*
#22000
1#
1*
#22025
0#
0*
#22050
1#
1*
#22075
0#
0*
#22100
1#
1*
#22125
0#
0*
#22150
1#
1*
#22175
0#
0*
#22200
1#
1'
0(
1*
1.
0/
#22225
0#
0*
#22250
1#
0'
1*
0.
#22275
0#
0*
#22300
1#
1*
#22325
0#
0*
#22350
1#
1*
#22375
0#
0*
#22400
1#
b00000110 $
b00000000000000000000000000011100 %
1'
1(
1*
b00000110 +
b00000000000000000000000000011100 ,
1.
1/
#22425
0#
0*
#22450
1#
0'
1*
0.
#22475
0#
0*
#22500
1#
1*
#22525
0#
0*
#22550
1#
1*
#22575
0#
0*
#22600
1#
1*
#22625
0#
0*
#22650
1#
1*
#22675
0#
0*
#22700
1#
1*
#22725
0#
0*
#22750
1#
1*
#22775
0#
0*
#22800
1#
1*
#22825
0#
0*
#22850
1#
1'
0(
1*
1.
0/
#22875
0#
0*
#22900
1#
0'
b00000000000000000000000000011100 )
1*
0.
b00000000000000000000000000011100 0
#22925
0#
0*
#22950
1#
1*
#22975
0#
0*
#23000
1#
1*
#23025
0#
0*
#23050
1#
1*
#23075
0#
0*
#23100
1#
1*
#23125
0#
0*
#23150
1#
1*
#23175
0#
0*
#23200
1#
1*
#23225
0#
0*
#23250
1#
1*
#23275
0#
0*
#23300
1#
1*
#23325
0#
0*
#23350
1#
b00000100 $
1'
1(
1*
b00000100 +
1.
1/
#23375
0#
0*
#23400
1#
0'
1*
0.
#23425
0#
0*
